envbox/__init__.py
envbox/base.py
envbox/cli.py
envbox/detectors.py
envbox/envs.py
envbox/settings.py
envbox/utils.py
envbox-2.0.1.dist-info/METADATA
envbox-2.0.1.dist-info/WHEEL
envbox-2.0.1.dist-info/entry_points.txt
envbox-2.0.1.dist-info/licenses/LICENSE
envbox-2.0.1.dist-info/RECORD
