Metadata-Version: 2.4
Name: envbox
Version: 2.0.1
Summary: Detect environment type and work within.
Project-URL: Homepage, https://github.com/idlesign/envbox
Project-URL: Documentation, https://envbox.readthedocs.io/
Author-email: Igor Starikov <idlesign@yandex.ru>
License-Expression: BSD-3-Clause
License-File: LICENSE
Keywords: backup,webinars
Requires-Python: >=3.10
Provides-Extra: cli
Requires-Dist: click>=2.0.0; extra == 'cli'
